[
  {
    "slug": "contact-backflowtestpros",
    "path": "/contact-backflowtestpros",
    "url": "https://www.backflowtestpros.com/contact-backflowtestpros",
    "family": "contact_page",
    "sourceTemplateFamily": "contact_page",
    "pageClass": "utility_legal",
    "title": "Backflow Test Pros - Contact Us | Same-Day Certification. Multi-Device Discount. Qualify for $500 Repair Coverage.",
    "metaDescription": "Contact us with your backflow testing, installation and repair questions. Qualify for $500 Repair Coverage. Multi-Device Discount. Same-Day Certification",
    "canonical": "https://www.backflowtestpros.com/contact-backflowtestpros",
    "h1": "Contact Us",
    "h2s": [
      "Schedule your backflow tests in advance to lock in your 2026 test pricing!"
    ],
    "h3s": [],
    "schemaTypes": [],
    "wordCount": 399,
    "primaryKeywordIntent": "contact backflowtestpros",
    "ctaPattern": [
      "call_now",
      "contact_form",
      "schedule",
      "pricing",
      "repair_coverage",
      "same_day_certification"
    ],
    "heroImage": "https://cdn.prod.website-files.com/67bfdff7943122ff2def874b/6813f5ea82607c502c2ec45d_Backflow%20Test%20Pros%20-%20Contact%20Us.avif",
    "hero": {
      "kind": "hero",
      "sourceClass": "simple-hero-section home-hero contact-page",
      "heading": "Contact Us",
      "body": "As licensed contractors, certified backflow experts and trusted cross connection control specialists, we provide Los Angeles, Ventura, Orange, San Diego and Riverside County residential and business communities turnkey backflow tests, installations, repairs services to keep our local water clean and ensure you avoid fines and civil liability. Everything Done for Your Backflow Installation, Testing & Repair. Guaranteed backflow testing compliance. Ask for Repair Coverage & Multi-location Discounts.",
      "primaryCta": null,
      "phoneCta": {
        "label": "(800) 803-6658",
        "href": "tel:+18008036658",
        "external": false,
        "target": ""
      }
    },
    "brandLogos": [],
    "sections": [
      {
        "kind": "hero",
        "sourceClass": "simple-hero-section home-hero contact-page",
        "heading": "Contact Us",
        "body": "As licensed contractors, certified backflow experts and trusted cross connection control specialists, we provide Los Angeles, Ventura, Orange, San Diego and Riverside County residential and business communities turnkey backflow tests, installations, repairs services to keep our local water clean and ensure you avoid fines and civil liability. Everything Done for Your Backflow Installation, Testing & Repair. Guaranteed backflow testing compliance. Ask for Repair Coverage & Multi-location Discounts.",
        "primaryCta": null,
        "phoneCta": {
          "label": "(800) 803-6658",
          "href": "tel:+18008036658",
          "external": false,
          "target": ""
        }
      },
      {
        "kind": "form_section",
        "sourceClass": "column-bullet-points-section dark-background-big-top-gap contact-page",
        "heading": "Schedule your backflow tests in advance to lock in your 2026 test pricing!",
        "body": "Backflow Test Pros' commitment to precision, reliability, and regulatory compliance has made us the preferred choice for businesses that demand the highest standards in state, county and municipal mandated backflow prevention testing and repairs. Contact us with your backflow service needs to experience the Backflow Test Pros \"Everything Done for Your\" service excellence.",
        "submitLabel": "send message",
        "formAction": "",
        "formMethod": "get",
        "fields": [
          {
            "label": "First name",
            "name": "first-name-2",
            "fieldType": "input",
            "inputType": "text",
            "placeholder": "First name",
            "required": true,
            "options": []
          },
          {
            "label": "Last name",
            "name": "last-name-2",
            "fieldType": "input",
            "inputType": "text",
            "placeholder": "Last name",
            "required": true,
            "options": []
          },
          {
            "label": "Company / property name",
            "name": "company_name",
            "fieldType": "input",
            "inputType": "text",
            "placeholder": "Company, HOA, or property name",
            "required": false,
            "options": []
          },
          {
            "label": "Phone",
            "name": "phone",
            "fieldType": "input",
            "inputType": "tel",
            "placeholder": "(555) 555-5555",
            "required": true,
            "options": []
          },
          {
            "label": "Email",
            "name": "email-field-2",
            "fieldType": "input",
            "inputType": "email",
            "placeholder": "you@email-provider.com",
            "required": true,
            "options": []
          },
          {
            "label": "Anything else we should know?",
            "name": "Message-Field-4",
            "fieldType": "textarea",
            "inputType": "textarea",
            "placeholder": "Optional notes like notice letters, failed tests, access details, or scheduling needs.",
            "required": false,
            "options": []
          }
        ]
      }
    ],
    "sectionKinds": [
      "hero",
      "form_section"
    ],
    "anomalyFlags": [],
    "anomalyRecords": [],
    "contactForm": {
      "kind": "form_section",
      "sourceClass": "column-bullet-points-section dark-background-big-top-gap contact-page",
      "heading": "Schedule your backflow tests in advance to lock in your 2026 test pricing!",
      "body": "Backflow Test Pros' commitment to precision, reliability, and regulatory compliance has made us the preferred choice for businesses that demand the highest standards in state, county and municipal mandated backflow prevention testing and repairs. Contact us with your backflow service needs to experience the Backflow Test Pros \"Everything Done for Your\" service excellence.",
      "submitLabel": "send message",
      "formAction": "",
      "formMethod": "get",
      "fields": [
        {
          "label": "First name",
          "name": "first-name-2",
          "fieldType": "input",
          "inputType": "text",
          "placeholder": "First name",
          "required": true,
          "options": []
        },
        {
          "label": "Last name",
          "name": "last-name-2",
          "fieldType": "input",
          "inputType": "text",
          "placeholder": "Last name",
          "required": true,
          "options": []
        },
        {
          "label": "Company / property name",
          "name": "company_name",
          "fieldType": "input",
          "inputType": "text",
          "placeholder": "Company, HOA, or property name",
          "required": false,
          "options": []
        },
        {
          "label": "Phone",
          "name": "phone",
          "fieldType": "input",
          "inputType": "tel",
          "placeholder": "(555) 555-5555",
          "required": true,
          "options": []
        },
        {
          "label": "Email",
          "name": "email-field-2",
          "fieldType": "input",
          "inputType": "email",
          "placeholder": "you@email-provider.com",
          "required": true,
          "options": []
        },
        {
          "label": "Anything else we should know?",
          "name": "Message-Field-4",
          "fieldType": "textarea",
          "inputType": "textarea",
          "placeholder": "Optional notes like notice letters, failed tests, access details, or scheduling needs.",
          "required": false,
          "options": []
        }
      ]
    }
  }
]
